{"results":[{"id":"795497539777","properties":{"company":"HubSpot","createdate":"2026-06-09T06:30:43.626Z","email":"emailmaria@hubspot.com","firstname":"Maria","hs_object_id":"795497539777","jobtitle":"Salesperson","lastmodifieddate":"2026-07-01T08:35:46.762Z","lastname":"Johnson (Sample Contact)"},"createdAt":"2026-06-09T06:30:43.626Z","updatedAt":"2026-07-01T08:35:46.762Z","archived":false,"url":"https://app-eu1.hubspot.com/contacts/148661610/record/0-1/795497539777"},{"id":"795523079383","properties":{"company":"HubSpot","createdate":"2026-06-09T06:30:44.216Z","email":"bh@hubspot.com","firstname":"Brian","hs_object_id":"795523079383","jobtitle":"Executive Chairperson","lastmodifieddate":"2026-07-01T08:35:38.314Z","lastname":"Halligan (Sample Contact)"},"createdAt":"2026-06-09T06:30:44.216Z","updatedAt":"2026-07-01T08:35:38.314Z","archived":false,"url":"https://app-eu1.hubspot.com/contacts/148661610/record/0-1/795523079383"}],"paging":{"next":{"after":"795523079384","link":"https://api.hubapi.com/crm/objects/v3/contacts?limit=2&properties=firstname%2Clastname%2Cemail%2Cjobtitle%2Ccompany&after=795523079384"}}}